treepro/__init__.py
treepro/cli.py
treepro/tree.py
treepro-0.1.5.dist-info/METADATA
treepro-0.1.5.dist-info/WHEEL
treepro-0.1.5.dist-info/entry_points.txt
treepro-0.1.5.dist-info/top_level.txt
treepro-0.1.5.dist-info/RECORD
