Metadata-Version: 2.4
Name: treepro
Version: 0.1.5
Summary: An advanced version of the Unix tree command.
Author: Your Name
Author-email: Your Name <your.email@example.com>
Requires-Dist: rich
Requires-Dist: click
Requires-Dist: questionary
Requires-Dist: pyyaml
Requires-Dist: pathspec
Requires-Dist: prompt_toolkit<3.0.47
Dynamic: author
